scientist/__init__.py
scientist_py-0.1.0.dist-info/licenses/LICENSE
scientist_py-0.1.0.dist-info/METADATA
scientist_py-0.1.0.dist-info/WHEEL
scientist_py-0.1.0.dist-info/top_level.txt
scientist_py-0.1.0.dist-info/RECORD
