Metadata-Version: 2.4
Name: scientist-py
Version: 0.1.0
Summary: A lightweight async-compatible experiment framework for safely comparing candidate code paths to control logic.
Author-email: Your Name <your@email.com>
License-Expression: MIT
Project-URL: Homepage, https://github.com/yourusername/scientist-py
Project-URL: Repository, https://github.com/yourusername/scientist-py
Requires-Python: >=3.8
License-File: LICENSE
Dynamic: license-file
